nlpurify/__init__.py
nlpurify/normalization.py
nlpurify/feature/__init__.py
nlpurify/feature/selection/__init__.py
nlpurify/feature/selection/nltk.py
nlpurify/fuzzy/__init__.py
nlpurify/fuzzy/logical.py
nlpurify/fuzzy/wrapper.py
nlpurify/legacy/__init__.py
nlpurify/legacy/nlp_utils.py
NLPurify-2.0.0a0.dist-info/LICENSE
NLPurify-2.0.0a0.dist-info/METADATA
NLPurify-2.0.0a0.dist-info/WHEEL
NLPurify-2.0.0a0.dist-info/top_level.txt
NLPurify-2.0.0a0.dist-info/RECORD
