Metadata-Version: 2.1
Name: NLPurify
Version: 2.0.0a0
Summary: Text cleaning and feature extractions using NLP, Traditional approach.
Home-page: https://github.com/sharkutilities/NLPurify
Author: shark-utilities developers
Author-email: neuralNOD@outlook.com
Project-URL: Issue Tracker, https://github.com/sharkutilities/NLPurify/issues
Project-URL: Org. Homepage, https://github.com/sharkutilities
Keywords: nlp,text-cleaning,nlp-cleaning,llm,utility,utilities,util,utils,functions,wrappers,data science,data analysis,data scientist,data analyst
Classifier: Development Status :: 1 - Planning
Classifier: Intended Audience :: Developers
Classifier: Intended Audience :: Education
Classifier: Intended Audience :: End Users/Desktop
Classifier: Intended Audience :: Information Technology
Classifier: Intended Audience :: Science/Research
Classifier: Operating System :: Unix
Classifier: Operating System :: POSIX
Classifier: Operating System :: Microsoft :: Windows
Classifier: Programming Language :: Python
Classifier: Programming Language :: Python :: 3
Classifier: Programming Language :: Python :: 3 :: Only
Classifier: Programming Language :: Python :: 3.8
Classifier: Programming Language :: Python :: 3.9
Classifier: Programming Language :: Python :: 3.10
Classifier: Programming Language :: Python :: 3.11
Classifier: Programming Language :: Python :: 3.12
Classifier: License :: OSI Approved :: MIT License
Requires-Python: >=3.8
License-File: LICENSE
